{"_type":"export","__export_format":4,"__export_date":"2024-03-12T01:10:13.729Z","__export_source":"insomnia.desktop.app:v8.6.1","resources":[{"_id":"req_326c67e1fc8c428d9edb9a62fef45fc7","parentId":"fld_6b44d669c39e49f78ccc4cdd0ac98534","modified":1710097915591,"created":1709040765218,"url":"http://localhost:3000/api/login/","name":"POST /api/login","description":"","method":"POST","body":{"mimeType":"application/json","text":"{\n\t\"pseudo\" : \"etml\",\n\t\"password\" : \"etml\"\n}\n"},"parameters":[],"headers":[{"name":"Content-Type","value":"application/json"},{"name":"User-Agent","value":"insomnia/8.6.1"}],"authentication":{},"metaSortKey":-1709642366197,"isPrivate":false,"pathParameters":[],"settingStoreCookies":true,"settingSendCookies":true,"settingDisableRenderRequestBody":false,"settingEncodeUrl":true,"settingRebuildPath":true,"settingFollowRedirects":"global","_type":"request"},{"_id":"fld_6b44d669c39e49f78ccc4cdd0ac98534","parentId":"wrk_b5acbbf91cbb4b87a2c129fb04bc52ee","modified":1709642359454,"created":1709642359454,"name":"/api/login","description":"","environment":{},"environmentPropertyOrder":null,"metaSortKey":-1709642359454,"_type":"request_group"},{"_id":"wrk_b5acbbf91cbb4b87a2c129fb04bc52ee","parentId":null,"modified":1710095496455,"created":1710095496455,"name":"LovBooksAPI","description":"","scope":"design","_type":"workspace"},{"_id":"req_5529c6b8ea824ede934d504afc688005","parentId":"fld_17e08377ddf04667b051288fc7d2fd5e","modified":1710098672204,"created":1709648671172,"url":"http://localhost:3000/api/categorys?name=Fantasy","name":"GET api/categorys?name=[name]","description":"","method":"GET","body":{},"parameters":[],"headers":[{"name":"User-Agent","value":"insomnia/8.6.1"}],"authentication":{},"metaSortKey":-1709642346656,"isPrivate":false,"pathParameters":[],"settingStoreCookies":true,"settingSendCookies":true,"settingDisableRenderRequestBody":false,"settingEncodeUrl":true,"settingRebuildPath":true,"settingFollowRedirects":"global","_type":"request"},{"_id":"fld_17e08377ddf04667b051288fc7d2fd5e","parentId":"wrk_b5acbbf91cbb4b87a2c129fb04bc52ee","modified":1709642434838,"created":1709642342237,"name":"/api/categorys/","description":"","environment":{},"environmentPropertyOrder":null,"metaSortKey":-1709642342237,"_type":"request_group"},{"_id":"req_80ccf0d1d0ea4a698392f4c3d52bfbed","parentId":"fld_17e08377ddf04667b051288fc7d2fd5e","modified":1710098686155,"created":1709650227129,"url":"http://localhost:3000/api/categorys/6/books","name":"GET api/categorys/(id)/books","description":"","method":"GET","body":{},"parameters":[],"headers":[{"name":"User-Agent","value":"insomnia/8.6.1"}],"authentication":{},"metaSortKey":-1709642346631,"isPrivate":false,"pathParameters":[],"settingStoreCookies":true,"settingSendCookies":true,"settingDisableRenderRequestBody":false,"settingEncodeUrl":true,"settingRebuildPath":true,"settingFollowRedirects":"global","_type":"request"},{"_id":"req_b49eb6acfe6940f69ca1154a9fd77180","parentId":"fld_17e08377ddf04667b051288fc7d2fd5e","modified":1710205653485,"created":1709642097112,"url":"http://localhost:3000/api/categorys/","name":"POST  /api/cetegorys/","description":"","method":"POST","body":{"mimeType":"application/json","text":"{\n\t\"name\":\"Fiction-Romance\"\n}"},"parameters":[],"headers":[{"name":"Content-Type","value":"application/json"},{"name":"User-Agent","value":"insomnia/8.6.1"}],"authentication":{},"metaSortKey":-1709642346556,"isPrivate":false,"pathParameters":[],"settingStoreCookies":true,"settingSendCookies":true,"settingDisableRenderRequestBody":false,"settingEncodeUrl":true,"settingRebuildPath":true,"settingFollowRedirects":"global","_type":"request"},{"_id":"req_b030104164c4491eb6328c19e144165c","parentId":"fld_17e08377ddf04667b051288fc7d2fd5e","modified":1710096253007,"created":1709642442676,"url":"http://localhost:3000/api/categorys/13","name":"DELETE /api/cetegorys/(ID)","description":"","method":"DELETE","body":{"mimeType":"application/json","text":""},"parameters":[],"headers":[{"name":"Content-Type","value":"application/json"},{"name":"User-Agent","value":"insomnia/8.6.1"}],"authentication":{},"metaSortKey":-1709642346506,"isPrivate":false,"pathParameters":[],"settingStoreCookies":true,"settingSendCookies":true,"settingDisableRenderRequestBody":false,"settingEncodeUrl":true,"settingRebuildPath":true,"settingFollowRedirects":"global","_type":"request"},{"_id":"req_598bba4e3c10459fb1220c480cccdb8b","parentId":"fld_17e08377ddf04667b051288fc7d2fd5e","modified":1710096260357,"created":1709642053115,"url":"http://localhost:3000/api/categorys/1","name":"GET  /api/cetegorys/(id)","description":"","method":"GET","body":{"mimeType":"application/json","text":"{\n\t\n}"},"parameters":[],"headers":[{"name":"Content-Type","value":"application/json"},{"name":"User-Agent","value":"insomnia/8.6.1"}],"authentication":{},"metaSortKey":-1709642346456,"isPrivate":false,"pathParameters":[],"settingStoreCookies":true,"settingSendCookies":true,"settingDisableRenderRequestBody":false,"settingEncodeUrl":true,"settingRebuildPath":true,"settingFollowRedirects":"global","_type":"request"},{"_id":"req_717e07a932514ac691606e6744ffd0d3","parentId":"fld_17e08377ddf04667b051288fc7d2fd5e","modified":1710096262820,"created":1709642396614,"url":"http://localhost:3000/api/categorys/1","name":"PUT  /api/cetegorys/(id)","description":"","method":"PUT","body":{"mimeType":"application/json","text":"{\n\t\n}"},"parameters":[],"headers":[{"name":"Content-Type","value":"application/json"},{"name":"User-Agent","value":"insomnia/8.6.1"}],"authentication":{},"metaSortKey":-1709642346406,"isPrivate":false,"pathParameters":[],"settingStoreCookies":true,"settingSendCookies":true,"settingDisableRenderRequestBody":false,"settingEncodeUrl":true,"settingRebuildPath":true,"settingFollowRedirects":"global","_type":"request"},{"_id":"req_17b301ffa51445098a9470b6ba4a9344","parentId":"fld_17e08377ddf04667b051288fc7d2fd5e","modified":1710096264766,"created":1709641258768,"url":"http://localhost:3000/api/categorys/","name":"GET  /api/cetegorys/","description":"","method":"GET","body":{},"parameters":[],"headers":[{"name":"User-Agent","value":"insomnia/8.6.1"}],"authentication":{},"metaSortKey":-1709642346356,"isPrivate":false,"pathParameters":[],"settingStoreCookies":true,"settingSendCookies":true,"settingDisableRenderRequestBody":false,"settingEncodeUrl":true,"settingRebuildPath":true,"settingFollowRedirects":"global","_type":"request"},{"_id":"req_4b1fb8e588074e91b03c867f0de10660","parentId":"fld_345491695d574da59014f9b2490958cc","modified":1710205640640,"created":1709643000275,"url":"http://localhost:3000/api/assessments/","name":"POST  /api/assessments/","description":"","method":"POST","body":{"mimeType":"application/json","text":"{\n\t\"assessment\":\"5\"\n}"},"parameters":[],"headers":[{"name":"Content-Type","value":"application/json"},{"name":"User-Agent","value":"insomnia/8.6.1"}],"authentication":{},"metaSortKey":-1709642346556,"isPrivate":false,"pathParameters":[],"settingStoreCookies":true,"settingSendCookies":true,"settingDisableRenderRequestBody":false,"settingEncodeUrl":true,"settingRebuildPath":true,"settingFollowRedirects":"global","_type":"request"},{"_id":"fld_345491695d574da59014f9b2490958cc","parentId":"wrk_b5acbbf91cbb4b87a2c129fb04bc52ee","modified":1709643000272,"created":1709643000272,"name":"/api/assessment/","description":"","environment":{},"environmentPropertyOrder":null,"metaSortKey":-1709642326148.5,"_type":"request_group"},{"_id":"req_7247fd2802dd4ccfa868b1e25ae8d85c","parentId":"fld_345491695d574da59014f9b2490958cc","modified":1710202957784,"created":1709643000276,"url":"http://localhost:3000/api/assessments/7","name":"DELETE /api/assessments/(id)","description":"","method":"DELETE","body":{"mimeType":"application/json","text":""},"parameters":[],"headers":[{"name":"Content-Type","value":"application/json"},{"name":"User-Agent","value":"insomnia/8.6.1"}],"authentication":{},"metaSortKey":-1709642346506,"isPrivate":false,"pathParameters":[],"settingStoreCookies":true,"settingSendCookies":true,"settingDisableRenderRequestBody":false,"settingEncodeUrl":true,"settingRebuildPath":true,"settingFollowRedirects":"global","_type":"request"},{"_id":"req_7b884e433f4e498ea32af33b5cfd57c7","parentId":"fld_345491695d574da59014f9b2490958cc","modified":1710096275416,"created":1709643000274,"url":"http://localhost:3000/api/assessments/1","name":"GET  /api/assessments/(id)","description":"","method":"GET","body":{"mimeType":"application/json","text":"{\n\t\n}"},"parameters":[],"headers":[{"name":"Content-Type","value":"application/json"},{"name":"User-Agent","value":"insomnia/8.6.1"}],"authentication":{},"metaSortKey":-1709642346456,"isPrivate":false,"pathParameters":[],"settingStoreCookies":true,"settingSendCookies":true,"settingDisableRenderRequestBody":false,"settingEncodeUrl":true,"settingRebuildPath":true,"settingFollowRedirects":"global","_type":"request"},{"_id":"req_0d1fe121159d4b488676d87bc3a083d9","parentId":"fld_345491695d574da59014f9b2490958cc","modified":1710096277537,"created":1709643000275,"url":"http://localhost:3000/api/assessments/1","name":"PUT  /api/assessments/(id)","description":"","method":"PUT","body":{"mimeType":"application/json","text":"{\n\t\n}"},"parameters":[],"headers":[{"name":"Content-Type","value":"application/json"},{"name":"User-Agent","value":"insomnia/8.6.1"}],"authentication":{},"metaSortKey":-1709642346406,"isPrivate":false,"pathParameters":[],"settingStoreCookies":true,"settingSendCookies":true,"settingDisableRenderRequestBody":false,"settingEncodeUrl":true,"settingRebuildPath":true,"settingFollowRedirects":"global","_type":"request"},{"_id":"req_cbc56e46570a4f4fa1596451f3d21cad","parentId":"fld_345491695d574da59014f9b2490958cc","modified":1710096279518,"created":1709643000273,"url":"http://localhost:3000/api/assessments/","name":"GET  /api/assessments/","description":"","method":"GET","body":{},"parameters":[],"headers":[{"name":"User-Agent","value":"insomnia/8.6.1"}],"authentication":{},"metaSortKey":-1709642346356,"isPrivate":false,"pathParameters":[],"settingStoreCookies":true,"settingSendCookies":true,"settingDisableRenderRequestBody":false,"settingEncodeUrl":true,"settingRebuildPath":true,"settingFollowRedirects":"global","_type":"request"},{"_id":"req_f91afce664da4524882e41337977f449","parentId":"fld_0f63b9c3e32e4ef58e41d55bb6d643da","modified":1710203109112,"created":1709648194454,"url":"http://localhost:3000/api/authors?name=Smith","name":"GET api/authors?name=[name]","description":"","method":"GET","body":{},"parameters":[],"headers":[{"name":"User-Agent","value":"insomnia/8.6.1"}],"authentication":{},"metaSortKey":-1709642346656,"isPrivate":false,"pathParameters":[],"settingStoreCookies":true,"settingSendCookies":true,"settingDisableRenderRequestBody":false,"settingEncodeUrl":true,"settingRebuildPath":true,"settingFollowRedirects":"global","_type":"request"},{"_id":"fld_0f63b9c3e32e4ef58e41d55bb6d643da","parentId":"wrk_b5acbbf91cbb4b87a2c129fb04bc52ee","modified":1709643363037,"created":1709643363037,"name":"/api/authors/","description":"","environment":{},"environmentPropertyOrder":null,"metaSortKey":-1709642318104.25,"_type":"request_group"},{"_id":"req_e8fd2a5aa52141d28fb6fa7cc7aab4b6","parentId":"fld_0f63b9c3e32e4ef58e41d55bb6d643da","modified":1709649240505,"created":1709649240505,"url":"http://localhost:3000/api/authors?first_name=Alice","name":"GET api/authors?first_name=[name]","description":"","method":"GET","body":{},"parameters":[],"headers":[{"name":"User-Agent","value":"insomnia/8.6.1"}],"authentication":{},"metaSortKey":-1709642346606,"isPrivate":false,"pathParameters":[],"settingStoreCookies":true,"settingSendCookies":true,"settingDisableRenderRequestBody":false,"settingEncodeUrl":true,"settingRebuildPath":true,"settingFollowRedirects":"global","_type":"request"},{"_id":"req_72aa4cf9966a4a09a599f30b0e8cdc87","parentId":"fld_0f63b9c3e32e4ef58e41d55bb6d643da","modified":1710205627400,"created":1709643363041,"url":"http://localhost:3000/api/authors/","name":"POST  /api/authors/","description":"","method":"POST","body":{"mimeType":"application/json","text":"{\n\t\"first_name\":\"Toledo\",\n\t\"name\": \"Adrian\"\n}"},"parameters":[],"headers":[{"name":"Content-Type","value":"application/json"},{"name":"User-Agent","value":"insomnia/8.6.1"}],"authentication":{},"metaSortKey":-1709642346556,"isPrivate":false,"pathParameters":[],"settingStoreCookies":true,"settingSendCookies":true,"settingDisableRenderRequestBody":false,"settingEncodeUrl":true,"settingRebuildPath":true,"settingFollowRedirects":"global","_type":"request"},{"_id":"req_72b576661e324342a8e96f5e2d6d5d63","parentId":"fld_0f63b9c3e32e4ef58e41d55bb6d643da","modified":1710096289613,"created":1709643363042,"url":"http://localhost:3000/api/authors/6","name":"DELETE /api/authors/(id)","description":"","method":"DELETE","body":{"mimeType":"application/json","text":""},"parameters":[],"headers":[{"name":"Content-Type","value":"application/json"},{"name":"User-Agent","value":"insomnia/8.6.1"}],"authentication":{},"metaSortKey":-1709642346506,"isPrivate":false,"pathParameters":[],"settingStoreCookies":true,"settingSendCookies":true,"settingDisableRenderRequestBody":false,"settingEncodeUrl":true,"settingRebuildPath":true,"settingFollowRedirects":"global","_type":"request"},{"_id":"req_64d0bee7fd1b458e8364d57be1a7322a","parentId":"fld_0f63b9c3e32e4ef58e41d55bb6d643da","modified":1710096291619,"created":1709643363039,"url":"http://localhost:3000/api/authors/1","name":"GET  /api/authors/(id)","description":"","method":"GET","body":{"mimeType":"application/json","text":"{\n\t\n}"},"parameters":[],"headers":[{"name":"Content-Type","value":"application/json"},{"name":"User-Agent","value":"insomnia/8.6.1"}],"authentication":{},"metaSortKey":-1709642346456,"isPrivate":false,"pathParameters":[],"settingStoreCookies":true,"settingSendCookies":true,"settingDisableRenderRequestBody":false,"settingEncodeUrl":true,"settingRebuildPath":true,"settingFollowRedirects":"global","_type":"request"},{"_id":"req_b4245db9031f4455b45f04f56afefb38","parentId":"fld_0f63b9c3e32e4ef58e41d55bb6d643da","modified":1710099536654,"created":1710098927833,"url":"http://localhost:3000/api/authors/3/books","name":"GET  /api/authors/(id)/books","description":"","method":"GET","body":{"mimeType":"application/json","text":""},"parameters":[],"headers":[{"name":"Content-Type","value":"application/json"},{"name":"User-Agent","value":"insomnia/8.6.1"}],"authentication":{},"metaSortKey":-1709642346431,"isPrivate":false,"pathParameters":[],"settingStoreCookies":true,"settingSendCookies":true,"settingDisableRenderRequestBody":false,"settingEncodeUrl":true,"settingRebuildPath":true,"settingFollowRedirects":"global","_type":"request"},{"_id":"req_e9258bca02884507a6424e120d271125","parentId":"fld_0f63b9c3e32e4ef58e41d55bb6d643da","modified":1710096293652,"created":1709643363040,"url":"http://localhost:3000/api/authors/1","name":"PUT  /api/authors/(id)","description":"","method":"PUT","body":{"mimeType":"application/json","text":"{\n\t\n}"},"parameters":[],"headers":[{"name":"Content-Type","value":"application/json"},{"name":"User-Agent","value":"insomnia/8.6.1"}],"authentication":{},"metaSortKey":-1709642346406,"isPrivate":false,"pathParameters":[],"settingStoreCookies":true,"settingSendCookies":true,"settingDisableRenderRequestBody":false,"settingEncodeUrl":true,"settingRebuildPath":true,"settingFollowRedirects":"global","_type":"request"},{"_id":"req_b194be6dd5754d5a8b411289ed9ed93d","parentId":"fld_0f63b9c3e32e4ef58e41d55bb6d643da","modified":1710096295598,"created":1709643363038,"url":"http://localhost:3000/api/authors/","name":"GET  /api/authors/","description":"","method":"GET","body":{},"parameters":[],"headers":[{"name":"User-Agent","value":"insomnia/8.6.1"}],"authentication":{},"metaSortKey":-1709642346356,"isPrivate":false,"pathParameters":[],"settingStoreCookies":true,"settingSendCookies":true,"settingDisableRenderRequestBody":false,"settingEncodeUrl":true,"settingRebuildPath":true,"settingFollowRedirects":"global","_type":"request"},{"_id":"req_bb3d1f8863404bf5ac1906857489ab54","parentId":"fld_6471f1741fca4640967d34c54e1b5f57","modified":1710205613953,"created":1709643593606,"url":"http://localhost:3000/api/comments/","name":"POST  /api/comments/","description":"","method":"POST","body":{"mimeType":"application/json","text":"{\n\"content\" : \"C'est super!\",\n\t\"book_id\" : 1\n}"},"parameters":[],"headers":[{"name":"Content-Type","value":"application/json"},{"name":"User-Agent","value":"insomnia/8.6.1"}],"authentication":{},"metaSortKey":-1709642346556,"isPrivate":false,"pathParameters":[],"settingStoreCookies":true,"settingSendCookies":true,"settingDisableRenderRequestBody":false,"settingEncodeUrl":true,"settingRebuildPath":true,"settingFollowRedirects":"global","_type":"request"},{"_id":"fld_6471f1741fca4640967d34c54e1b5f57","parentId":"wrk_b5acbbf91cbb4b87a2c129fb04bc52ee","modified":1709643776970,"created":1709643593602,"name":"/api/comments/","description":"","environment":{},"environmentPropertyOrder":null,"metaSortKey":-1709642314082.125,"_type":"request_group"},{"_id":"req_39793809c71a44a3974397db6acafe7c","parentId":"fld_6471f1741fca4640967d34c54e1b5f57","modified":1710096302201,"created":1709643593607,"url":"http://localhost:3000/api/comments/6","name":"DELETE /api/comments/(id)","description":"","method":"DELETE","body":{"mimeType":"application/json","text":""},"parameters":[],"headers":[{"name":"Content-Type","value":"application/json"},{"name":"User-Agent","value":"insomnia/8.6.1"}],"authentication":{},"metaSortKey":-1709642346506,"isPrivate":false,"pathParameters":[],"settingStoreCookies":true,"settingSendCookies":true,"settingDisableRenderRequestBody":false,"settingEncodeUrl":true,"settingRebuildPath":true,"settingFollowRedirects":"global","_type":"request"},{"_id":"req_69d060502c3e43d9a78aa5b88d18b851","parentId":"fld_6471f1741fca4640967d34c54e1b5f57","modified":1710102128164,"created":1709643593604,"url":"http://localhost:3000/api/comments/2","name":"GET  /api/comments/(id)","description":"","method":"GET","body":{"mimeType":"application/json","text":"{\n\t\n}"},"parameters":[],"headers":[{"name":"Content-Type","value":"application/json"},{"name":"User-Agent","value":"insomnia/8.6.1"}],"authentication":{},"metaSortKey":-1709642346456,"isPrivate":false,"pathParameters":[],"settingStoreCookies":true,"settingSendCookies":true,"settingDisableRenderRequestBody":false,"settingEncodeUrl":true,"settingRebuildPath":true,"settingFollowRedirects":"global","_type":"request"},{"_id":"req_572a4aab959c41b7a27acc1b57b93f86","parentId":"fld_6471f1741fca4640967d34c54e1b5f57","modified":1710096307437,"created":1709643593605,"url":"http://localhost:3000/api/comments/1","name":"PUT  /api/comments/(id)","description":"","method":"PUT","body":{"mimeType":"application/json","text":"{\n\t\n}"},"parameters":[],"headers":[{"name":"Content-Type","value":"application/json"},{"name":"User-Agent","value":"insomnia/8.6.1"}],"authentication":{},"metaSortKey":-1709642346406,"isPrivate":false,"pathParameters":[],"settingStoreCookies":true,"settingSendCookies":true,"settingDisableRenderRequestBody":false,"settingEncodeUrl":true,"settingRebuildPath":true,"settingFollowRedirects":"global","_type":"request"},{"_id":"req_90e7782c4f454668882385b80efb324f","parentId":"fld_6471f1741fca4640967d34c54e1b5f57","modified":1710096309249,"created":1709643593603,"url":"http://localhost:3000/api/comments/","name":"GET  /api/comments/","description":"","method":"GET","body":{},"parameters":[],"headers":[{"name":"User-Agent","value":"insomnia/8.6.1"}],"authentication":{},"metaSortKey":-1709642346356,"isPrivate":false,"pathParameters":[],"settingStoreCookies":true,"settingSendCookies":true,"settingDisableRenderRequestBody":false,"settingEncodeUrl":true,"settingRebuildPath":true,"settingFollowRedirects":"global","_type":"request"},{"_id":"req_ddba2d73e9a84d179ed4e1a532cea448","parentId":"fld_c6f605f5ee3746f38ab95c6d8c18711c","modified":1709649084801,"created":1709649057573,"url":"http://localhost:3000/api/publishers?name=Shueisha","name":"GET api/publishers?name=[name]","description":"","method":"GET","body":{},"parameters":[],"headers":[{"name":"User-Agent","value":"insomnia/8.6.1"}],"authentication":{},"metaSortKey":-1709642346656,"isPrivate":false,"pathParameters":[],"settingStoreCookies":true,"settingSendCookies":true,"settingDisableRenderRequestBody":false,"settingEncodeUrl":true,"settingRebuildPath":true,"settingFollowRedirects":"global","_type":"request"},{"_id":"fld_c6f605f5ee3746f38ab95c6d8c18711c","parentId":"wrk_b5acbbf91cbb4b87a2c129fb04bc52ee","modified":1709643697753,"created":1709643697753,"name":"/api/publishers/","description":"","environment":{},"environmentPropertyOrder":null,"metaSortKey":-1709642312071.0625,"_type":"request_group"},{"_id":"req_d9114b692aec4234b863e3d88db746ad","parentId":"fld_c6f605f5ee3746f38ab95c6d8c18711c","modified":1710205599104,"created":1709643697756,"url":"http://localhost:3000/api/publishers/","name":"POST  /api/publishers/","description":"","method":"POST","body":{"mimeType":"application/json","text":"{\n\"name\" : \"BandaiNamco\"\n}"},"parameters":[],"headers":[{"name":"Content-Type","value":"application/json"},{"name":"User-Agent","value":"insomnia/8.6.1"}],"authentication":{},"metaSortKey":-1709642346556,"isPrivate":false,"pathParameters":[],"settingStoreCookies":true,"settingSendCookies":true,"settingDisableRenderRequestBody":false,"settingEncodeUrl":true,"settingRebuildPath":true,"settingFollowRedirects":"global","_type":"request"},{"_id":"req_d4a91a41ad124858a371632ad095cecd","parentId":"fld_c6f605f5ee3746f38ab95c6d8c18711c","modified":1710203637008,"created":1709643697757,"url":"http://localhost:3000/api/publishers/4","name":"DELETE /api/publishers/(id)","description":"","method":"DELETE","body":{"mimeType":"application/json","text":""},"parameters":[],"headers":[{"name":"Content-Type","value":"application/json"},{"name":"User-Agent","value":"insomnia/8.6.1"}],"authentication":{},"metaSortKey":-1709642346506,"isPrivate":false,"pathParameters":[],"settingStoreCookies":true,"settingSendCookies":true,"settingDisableRenderRequestBody":false,"settingEncodeUrl":true,"settingRebuildPath":true,"settingFollowRedirects":"global","_type":"request"},{"_id":"req_c9f23de00e554f26805c7b13bb1f695e","parentId":"fld_c6f605f5ee3746f38ab95c6d8c18711c","modified":1710096324474,"created":1709643697755,"url":"http://localhost:3000/api/publishers/1","name":"GET  /api/publishers/(id)","description":"","method":"GET","body":{"mimeType":"application/json","text":"{\n\t\n}"},"parameters":[],"headers":[{"name":"Content-Type","value":"application/json"},{"name":"User-Agent","value":"insomnia/8.6.1"}],"authentication":{},"metaSortKey":-1709642346456,"isPrivate":false,"pathParameters":[],"settingStoreCookies":true,"settingSendCookies":true,"settingDisableRenderRequestBody":false,"settingEncodeUrl":true,"settingRebuildPath":true,"settingFollowRedirects":"global","_type":"request"},{"_id":"req_bef7203030d4499eac7cbf146068ecd3","parentId":"fld_c6f605f5ee3746f38ab95c6d8c18711c","modified":1710096326984,"created":1709643697755,"url":"http://localhost:3000/api/publishers/1","name":"PUT  /api/publishers/(id)","description":"","method":"PUT","body":{"mimeType":"application/json","text":"{\n\t\n}"},"parameters":[],"headers":[{"name":"Content-Type","value":"application/json"},{"name":"User-Agent","value":"insomnia/8.6.1"}],"authentication":{},"metaSortKey":-1709642346406,"isPrivate":false,"pathParameters":[],"settingStoreCookies":true,"settingSendCookies":true,"settingDisableRenderRequestBody":false,"settingEncodeUrl":true,"settingRebuildPath":true,"settingFollowRedirects":"global","_type":"request"},{"_id":"req_7e43770128a7418d859da92a05209c09","parentId":"fld_c6f605f5ee3746f38ab95c6d8c18711c","modified":1710096328847,"created":1709643697754,"url":"http://localhost:3000/api/publishers/","name":"GET  /api/publishers/","description":"","method":"GET","body":{},"parameters":[],"headers":[{"name":"User-Agent","value":"insomnia/8.6.1"}],"authentication":{},"metaSortKey":-1709642346356,"isPrivate":false,"pathParameters":[],"settingStoreCookies":true,"settingSendCookies":true,"settingDisableRenderRequestBody":false,"settingEncodeUrl":true,"settingRebuildPath":true,"settingFollowRedirects":"global","_type":"request"},{"_id":"req_ae5c3ec693ca417a845580157e524808","parentId":"fld_fd33fefa103546ca8ebf99ac94c3844c","modified":1709649174980,"created":1709649111022,"url":"http://localhost:3000/api/users?pseudo=gourmet45","name":"GET api/users?name=[name]","description":"","method":"GET","body":{},"parameters":[],"headers":[{"name":"User-Agent","value":"insomnia/8.6.1"}],"authentication":{},"metaSortKey":-1709642269655,"isPrivate":false,"pathParameters":[],"settingStoreCookies":true,"settingSendCookies":true,"settingDisableRenderRequestBody":false,"settingEncodeUrl":true,"settingRebuildPath":true,"settingFollowRedirects":"global","_type":"request"},{"_id":"fld_fd33fefa103546ca8ebf99ac94c3844c","parentId":"wrk_b5acbbf91cbb4b87a2c129fb04bc52ee","modified":1709643849911,"created":1709642253270,"name":"/api/users/","description":"","environment":{},"environmentPropertyOrder":null,"metaSortKey":-1709642297370.7969,"_type":"request_group"},{"_id":"req_51e89008113c4e848ec6b47f2aca92b0","parentId":"fld_fd33fefa103546ca8ebf99ac94c3844c","modified":1710096335829,"created":1709537280504,"url":"http://localhost:3000/api/users","name":"GET /api/users","description":"","method":"GET","body":{},"parameters":[],"headers":[{"name":"User-Agent","value":"insomnia/8.6.1"}],"authentication":{},"metaSortKey":-1709642269555,"isPrivate":false,"pathParameters":[],"settingStoreCookies":true,"settingSendCookies":true,"settingDisableRenderRequestBody":false,"settingEncodeUrl":true,"settingRebuildPath":true,"settingFollowRedirects":"global","_type":"request"},{"_id":"req_888d7109d97a483d948391944026a451","parentId":"fld_fd33fefa103546ca8ebf99ac94c3844c","modified":1710096338373,"created":1709537642452,"url":"http://localhost:3000/api/users/1","name":"GET /api/users/(id)","description":"","method":"GET","body":{},"parameters":[],"headers":[{"name":"User-Agent","value":"insomnia/8.6.1"}],"authentication":{},"metaSortKey":-1709642269530,"isPrivate":false,"pathParameters":[],"settingStoreCookies":true,"settingSendCookies":true,"settingDisableRenderRequestBody":false,"settingEncodeUrl":true,"settingRebuildPath":true,"settingFollowRedirects":"global","_type":"request"},{"_id":"req_d3f2573588e640c694f9453a4b7ce98d","parentId":"fld_fd33fefa103546ca8ebf99ac94c3844c","modified":1710099971989,"created":1710099841054,"url":"http://localhost:3000/api/users/1/books","name":"GET /api/users/(id)/books","description":"","method":"GET","body":{},"parameters":[],"headers":[{"name":"User-Agent","value":"insomnia/8.6.1"}],"authentication":{},"metaSortKey":-1709642269523.75,"isPrivate":false,"pathParameters":[],"settingStoreCookies":true,"settingSendCookies":true,"settingDisableRenderRequestBody":false,"settingEncodeUrl":true,"settingRebuildPath":true,"settingFollowRedirects":"global","_type":"request"},{"_id":"req_7a94a4ec8e424c64871903af2adb6cf2","parentId":"fld_fd33fefa103546ca8ebf99ac94c3844c","modified":1710205588176,"created":1709537703680,"url":"http://localhost:3000/api/users/","name":"POST /api/users","description":"","method":"POST","body":{"mimeType":"application/json","text":"{\n\t\"pseudo\" : \"etmlsd\",\n\t\"date_enter\": \"2000-01-15T00:00:00.000Z\",\n\t\"password\" : \"etml2\"\n}\n\n\n"},"parameters":[],"headers":[{"name":"Content-Type","value":"application/json"},{"name":"User-Agent","value":"insomnia/8.6.1"}],"authentication":{},"metaSortKey":-1709642269517.5,"isPrivate":false,"pathParameters":[],"settingStoreCookies":true,"settingSendCookies":true,"settingDisableRenderRequestBody":false,"settingEncodeUrl":true,"settingRebuildPath":true,"settingFollowRedirects":"global","_type":"request"},{"_id":"req_a6914f7ce6594fab911138dbf36b63d0","parentId":"fld_fd33fefa103546ca8ebf99ac94c3844c","modified":1710096343758,"created":1709545959241,"url":"http://localhost:3000/api/users/1","name":"PUT  /api/users/(id)","description":"","method":"PUT","body":{"mimeType":"application/json","text":"{\n\t\"pseudo\" : \"voyageur79\"\n}"},"parameters":[],"headers":[{"name":"Content-Type","value":"application/json"},{"name":"User-Agent","value":"insomnia/8.6.1"}],"authentication":{},"metaSortKey":-1709642269505,"isPrivate":false,"pathParameters":[],"settingStoreCookies":true,"settingSendCookies":true,"settingDisableRenderRequestBody":false,"settingEncodeUrl":true,"settingRebuildPath":true,"settingFollowRedirects":"global","_type":"request"},{"_id":"req_95113ff1888e4c6986a875d02685cd2a","parentId":"fld_fd33fefa103546ca8ebf99ac94c3844c","modified":1710096346130,"created":1709545741454,"url":"http://localhost:3000/api/users/2","name":"DELETE  /api/users/(id)","description":"","method":"DELETE","body":{"mimeType":"application/json","text":""},"parameters":[],"headers":[{"name":"Content-Type","value":"application/json"},{"name":"User-Agent","value":"insomnia/8.6.1"}],"authentication":{},"metaSortKey":-1709642269405,"isPrivate":false,"pathParameters":[],"settingStoreCookies":true,"settingSendCookies":true,"settingDisableRenderRequestBody":false,"settingEncodeUrl":true,"settingRebuildPath":true,"settingFollowRedirects":"global","_type":"request"},{"_id":"req_98044678a3fe430c95e588caa8f4ae52","parentId":"fld_2d892ea44b2f46bca9b6cb31aeca5ecd","modified":1709648169377,"created":1709647886649,"url":"http://localhost:3000/api/books?title=Fondation","name":"GET api/books?title=[name]","description":"","method":"GET","body":{},"parameters":[],"headers":[{"name":"User-Agent","value":"insomnia/8.6.1"}],"authentication":{},"metaSortKey":-1709647886649,"isPrivate":false,"pathParameters":[],"settingStoreCookies":true,"settingSendCookies":true,"settingDisableRenderRequestBody":false,"settingEncodeUrl":true,"settingRebuildPath":true,"settingFollowRedirects":"global","_type":"request"},{"_id":"fld_2d892ea44b2f46bca9b6cb31aeca5ecd","parentId":"wrk_b5acbbf91cbb4b87a2c129fb04bc52ee","modified":1709643847899,"created":1709642310060,"name":"/api/books/","description":"","environment":{},"environmentPropertyOrder":null,"metaSortKey":-1709642282670.5312,"_type":"request_group"},{"_id":"req_8741c28e3ce2417594edb9bddde252c3","parentId":"fld_2d892ea44b2f46bca9b6cb31aeca5ecd","modified":1710114433950,"created":1708939879485,"url":"http://localhost:3000/api/books/3","name":"GET api/books/(id)","description":"","method":"GET","body":{},"parameters":[],"headers":[{"name":"User-Agent","value":"insomnia/8.6.1"}],"authentication":{},"metaSortKey":-1709642320160,"isPrivate":false,"pathParameters":[],"settingStoreCookies":true,"settingSendCookies":true,"settingDisableRenderRequestBody":false,"settingEncodeUrl":true,"settingRebuildPath":true,"settingFollowRedirects":"global","_type":"request"},{"_id":"req_bfb1a5ea3fd7479b9ad37eb3e2a27aab","parentId":"fld_2d892ea44b2f46bca9b6cb31aeca5ecd","modified":1710115492114,"created":1710100451168,"url":"http://localhost:3000/api/books/2/comments","name":"GET api/books/(id)/comments","description":"","method":"GET","body":{"mimeType":"application/json","text":"{\n\t\n}"},"parameters":[],"headers":[{"name":"Content-Type","value":"application/json"},{"name":"User-Agent","value":"insomnia/8.6.1"}],"authentication":{},"metaSortKey":-1709642320110,"isPrivate":false,"pathParameters":[],"settingStoreCookies":true,"settingSendCookies":true,"settingDisableRenderRequestBody":false,"settingEncodeUrl":true,"settingRebuildPath":true,"settingFollowRedirects":"global","_type":"request"},{"_id":"req_3a44fd2bcb9d46358040a0f8c25e756d","parentId":"fld_2d892ea44b2f46bca9b6cb31aeca5ecd","modified":1710117346499,"created":1710100663844,"url":"http://localhost:3000/api/books/2/notes","name":"GET api/books/(id)/notes","description":"","method":"GET","body":{},"parameters":[],"headers":[{"name":"User-Agent","value":"insomnia/8.6.1"}],"authentication":{},"metaSortKey":-1709642320085,"isPrivate":false,"pathParameters":[],"settingStoreCookies":true,"settingSendCookies":true,"settingDisableRenderRequestBody":false,"settingEncodeUrl":true,"settingRebuildPath":true,"settingFollowRedirects":"global","_type":"request"},{"_id":"req_cfbf12bdf6f44adc8d20e94ec6c3a36d","parentId":"fld_2d892ea44b2f46bca9b6cb31aeca5ecd","modified":1710096221233,"created":1708939802423,"url":"http://localhost:3000/api/books/","name":"GET api/books","description":"","method":"GET","body":{"mimeType":"application/json","text":""},"parameters":[],"headers":[{"name":"Content-Type","value":"application/json","id":"pair_3000bbbaac394f51bc2bee03bfbe9d03","disabled":false},{"name":"User-Agent","value":"insomnia/8.6.1","id":"pair_1013f4716c6243e484116b3110a2a3cf"},{"id":"pair_a36e1af690da4883be73c521bba7b2c3","name":"authorization","value":"Bearer eyJhbGciOiJIUzI1NiIsInR5cCI6IkpXVCJ9.eyJjdXN0b21lcklkIjoyLCJpYXQiOjE3MDk1NDU0MDYsImV4cCI6MTc0MTEwMzAwNn0.-wmpKpKJkUmsm-YQCwtF1ij44v2OQv6J7AsmP0cLpew","description":""}],"authentication":{"type":"apikey","disabled":true,"key":"CUSTOME_PRIVATE_KEY","value":"","addTo":"header"},"metaSortKey":-1709642320060,"isPrivate":false,"pathParameters":[],"settingStoreCookies":true,"settingSendCookies":true,"settingDisableRenderRequestBody":false,"settingEncodeUrl":true,"settingRebuildPath":true,"settingFollowRedirects":"global","_type":"request"},{"_id":"req_ab592520bbb14ba996d9f1d83113cc64","parentId":"fld_2d892ea44b2f46bca9b6cb31aeca5ecd","modified":1710096235351,"created":1708941774949,"url":"http://localhost:3000/api/books/2","name":"PUT /api/books/(id)","description":"","method":"PUT","body":{"mimeType":"application/json","text":"{\n\t\"name\" : \"Apocalypse  II : The Revange\",\n\t\"pages\" : 161\n}"},"parameters":[],"headers":[{"name":"Content-Type","value":"application/json"},{"name":"User-Agent","value":"insomnia/8.6.1"}],"authentication":{},"metaSortKey":-1709642320010,"isPrivate":false,"pathParameters":[],"settingStoreCookies":true,"settingSendCookies":true,"settingDisableRenderRequestBody":false,"settingEncodeUrl":true,"settingRebuildPath":true,"settingFollowRedirects":"global","_type":"request"},{"_id":"req_ae8bbc68f5c14f91b1cb61a594012f59","parentId":"fld_2d892ea44b2f46bca9b6cb31aeca5ecd","modified":1710096232823,"created":1708941837174,"url":"http://localhost:3000/api/books/3","name":"DELETE /api/books/(id)","description":"","method":"DELETE","body":{},"parameters":[],"headers":[{"name":"User-Agent","value":"insomnia/8.6.1"}],"authentication":{},"metaSortKey":-1709642319985,"isPrivate":false,"pathParameters":[],"settingStoreCookies":true,"settingSendCookies":true,"settingDisableRenderRequestBody":false,"settingEncodeUrl":true,"settingRebuildPath":true,"settingFollowRedirects":"global","_type":"request"},{"_id":"req_6251f1927461485d9306622066d962e4","parentId":"fld_2d892ea44b2f46bca9b6cb31aeca5ecd","modified":1710204854920,"created":1708941667144,"url":"http://localhost:3000/api/books/","name":"POST /api/books/","description":"","method":"POST","body":{"mimeType":"application/json","text":"{\n\t\"title\" : \"Apocalypse III2 : The end\",\n\t\"number_of_pages\" : 161,\n\t\"year_of_publication\" : 1999,\n\t\"cover_image\":\"xd\",\n\t\"extract_pdf\":\" xd\",\n\t\"category_id\":11,\n\t\"summary\": \"xd\"\t\n}"},"parameters":[],"headers":[{"name":"Content-Type","value":"application/json"},{"name":"User-Agent","value":"insomnia/8.6.1"}],"authentication":{},"metaSortKey":-1709642319960,"isPrivate":false,"pathParameters":[],"settingStoreCookies":true,"settingSendCookies":true,"settingDisableRenderRequestBody":false,"settingEncodeUrl":true,"settingRebuildPath":true,"settingFollowRedirects":"global","_type":"request"},{"_id":"req_d407e1c77df44f8c8f434a44cc91e58a","parentId":"fld_2d892ea44b2f46bca9b6cb31aeca5ecd","modified":1710205509337,"created":1710103790430,"url":"http://localhost:3000/api/books/2/comments","name":"POST /api/books/(id)/comments","description":"","method":"POST","body":{"mimeType":"application/json","text":"{\n\t\"content\":\"C'est le mieux livre <3\"\n}"},"parameters":[],"headers":[{"name":"Content-Type","value":"application/json"},{"name":"User-Agent","value":"insomnia/8.6.1"}],"authentication":{},"metaSortKey":-1709642294807.5,"isPrivate":false,"pathParameters":[],"settingStoreCookies":true,"settingSendCookies":true,"settingDisableRenderRequestBody":false,"settingEncodeUrl":true,"settingRebuildPath":true,"settingFollowRedirects":"global","_type":"request"},{"_id":"req_69d1968ed2a443c396c51dd0bfa53207","parentId":"fld_2d892ea44b2f46bca9b6cb31aeca5ecd","modified":1710205502467,"created":1710117264368,"url":"http://localhost:3000/api/books/2/note","name":"POST /api/books/(id)/note","description":"","method":"POST","body":{"mimeType":"application/json","text":"{\n\t\"assessment\": 5\n}"},"parameters":[],"headers":[{"name":"Content-Type","value":"application/json"},{"name":"User-Agent","value":"insomnia/8.6.1"}],"authentication":{},"metaSortKey":-1709642282231.25,"isPrivate":false,"pathParameters":[],"settingStoreCookies":true,"settingSendCookies":true,"settingDisableRenderRequestBody":false,"settingEncodeUrl":true,"settingRebuildPath":true,"settingFollowRedirects":"global","_type":"request"},{"_id":"env_9e41e4a2f12f0869668a456ad5fa2221634be8e5","parentId":"wrk_b5acbbf91cbb4b87a2c129fb04bc52ee","modified":1710095496463,"created":1710095496463,"name":"Base Environment","data":{},"dataPropertyOrder":null,"color":null,"isPrivate":false,"metaSortKey":1710095496463,"_type":"environment"},{"_id":"jar_9e41e4a2f12f0869668a456ad5fa2221634be8e5","parentId":"wrk_b5acbbf91cbb4b87a2c129fb04bc52ee","modified":1710095496466,"created":1710095496466,"name":"Default Jar","cookies":[],"_type":"cookie_jar"},{"_id":"spc_73dcc5578e0e4a5697cdf585c6e14f84","parentId":"wrk_b5acbbf91cbb4b87a2c129fb04bc52ee","modified":1710199378082,"created":1710095496459,"fileName":"LovBooksAPI","contents":"","contentType":"yaml","_type":"api_spec"}]}